decampy/__init__.py
decampy-0.1.0.dist-info/LICENSE
decampy-0.1.0.dist-info/METADATA
decampy-0.1.0.dist-info/WHEEL
decampy-0.1.0.dist-info/top_level.txt
decampy-0.1.0.dist-info/RECORD
